easy_image_labeling/__init__.py
easy_image_labeling/cli.py
easy_image_labeling/config.py
easy_image_labeling/dataset_manager.py
easy_image_labeling/exceptions.py
easy_image_labeling/forms.py
easy_image_labeling/helper_functions.py
easy_image_labeling/main.py
easy_image_labeling/result_writers.py
easy_image_labeling/db/db.py
easy_image_labeling/db/schema.sql
easy_image_labeling/pages/classify.py
easy_image_labeling/pages/export.py
easy_image_labeling/pages/selection.py
easy_image_labeling/plotlydash/dashboard.py
easy_image_labeling/plotlydash/assets/dash_style.css
easy_image_labeling/plotlydash/components/ids.py
easy_image_labeling/plotlydash/components/layout.py
easy_image_labeling/plotlydash/components/pie_chart.py
easy_image_labeling/plotlydash/components/progress_chart.py
easy_image_labeling/plotlydash/components/sidebar.py
easy_image_labeling/plotlydash/data/data_loader.py
easy_image_labeling/plotlydash/data/source.py
easy_image_labeling/static/style.css
easy_image_labeling/templates/_formhelpers.html
easy_image_labeling/templates/base.html
easy_image_labeling/templates/class_names.html
easy_image_labeling/templates/class_number.html
easy_image_labeling/templates/classification_summary.html
easy_image_labeling/templates/classify_image.html
easy_image_labeling/templates/dataset_selection.html
easy_image_labeling/templates/export_results.html
easy_image_labeling/templates/index.html
easy_image_labeling/templates/remove_datasets.html
easy_image_labeling/templates/upload_dataset.html
easy_image_labeling-2.2.0.dist-info/licenses/LICENSE
easy_image_labeling-2.2.0.dist-info/METADATA
easy_image_labeling-2.2.0.dist-info/WHEEL
easy_image_labeling-2.2.0.dist-info/entry_points.txt
easy_image_labeling-2.2.0.dist-info/top_level.txt
easy_image_labeling-2.2.0.dist-info/RECORD
